yumpu_sdk/api.py
yumpu_sdk/__init__.py
yumpu_sdk-0.1.7.dist-info/WHEEL
yumpu_sdk-0.1.7.dist-info/top_level.txt
yumpu_sdk-0.1.7.dist-info/DESCRIPTION.rst
yumpu_sdk-0.1.7.dist-info/entry_points.txt
yumpu_sdk-0.1.7.dist-info/METADATA
yumpu_sdk-0.1.7.dist-info/metadata.json
yumpu_sdk-0.1.7.dist-info/pbr.json
yumpu_sdk-0.1.7.dist-info/RECORD
