Metadata-Version: 2.0
Name: yumpu-sdk
Version: 0.1.7
Summary: Python SDK for Yumpu API
Home-page: https://github.com/gnunixon/python-yumpu-sdk
Author: Viorel Roman
Author-email: mail@viorel-roman.org
License: GPLv3+
Keywords: convert pdf files to web optimized e-papers by Yumpu API
Platform: UNKNOWN
Classifier: Development Status :: 5 - Production/Stable
Classifier: Intended Audience :: Developers
Classifier: Topic :: Software Development :: Libraries :: Python Modules
Classifier: License :: OSI Approved :: GNU General Public License v3 or later (GPLv3+)
Classifier: Programming Language :: Python :: 2
Classifier: Programming Language :: Python :: 2.7
Classifier: Programming Language :: Python :: 3
Classifier: Programming Language :: Python :: 3.2
Classifier: Programming Language :: Python :: 3.3
Classifier: Programming Language :: Python :: 3.4
Classifier: Operating System :: OS Independent
Requires-Dist: requests
